tamal/__init__.py
tamal/_wrap.py
tamal/defaults.py
tamal/py.typed
tamal-0.2.0.dist-info/METADATA
tamal-0.2.0.dist-info/WHEEL
tamal-0.2.0.dist-info/RECORD
