Metadata-Version: 2.1
Name: tamal
Version: 0.2.0
Summary: A library for wrapping text
Author: Jonathan Herrera
Author-email: jonathan.herrera@posteo.de
Requires-Python: >=3.12,<4.0
Classifier: Programming Language :: Python :: 3
Classifier: Programming Language :: Python :: 3.12
Project-URL: bugs, https://github.com/jnthnhrrr/python-tamal/issues
Project-URL: docs, https://jnthnhrrr.github.io/python-tamal
Project-URL: source, https://github.com/jnthnhrrr/python-tamal
